markunder/__init__.py
markunder-0.0.1.dist-info/WHEEL
markunder-0.0.1.dist-info/METADATA
markunder-0.0.1.dist-info/RECORD
